berapi/__init__.py
berapi/client.py
berapi/config/__init__.py
berapi/config/settings.py
berapi/exceptions/__init__.py
berapi/exceptions/errors.py
berapi/http/__init__.py
berapi/http/retry.py
berapi/http/session.py
berapi/logging/__init__.py
berapi/logging/setup.py
berapi/middleware/__init__.py
berapi/middleware/auth.py
berapi/middleware/base.py
berapi/middleware/chain.py
berapi/middleware/logging.py
berapi/py.typed
berapi/response/__init__.py
berapi/response/response.py
berapi/utils/__init__.py
berapi/utils/curl.py
berapi/utils/json_path.py
berapi/validation/__init__.py
berapi/validation/json_schema.py
berapi/validation/openapi.py
berapi-2.2.0.dist-info/METADATA
berapi-2.2.0.dist-info/WHEEL
berapi-2.2.0.dist-info/licenses/LICENSE
berapi-2.2.0.dist-info/RECORD
