Metadata-Version: 2.4
Name: berapi
Version: 2.2.0
Summary: A modern, scalable API testing library for Python with middleware support, structured logging, and fluent assertions
License: MIT
License-File: LICENSE
Keywords: api,testing,pytest,http,rest,api-client,middleware,assertions
Author: fachrulch
Author-email: hello@ngetest.id
Requires-Python: >=3.12,<4.0
Classifier: Development Status :: 4 - Beta
Classifier: Intended Audience :: Developers
Classifier: License :: OSI Approved :: MIT License
Classifier: Programming Language :: Python :: 3
Classifier: Programming Language :: Python :: 3.12
Classifier: Programming Language :: Python :: 3.13
Classifier: Programming Language :: Python :: 3.14
Classifier: Topic :: Internet :: WWW/HTTP
Classifier: Topic :: Software Development :: Testing
Classifier: Typing :: Typed
Requires-Dist: genson (>=1.3.0,<2.0.0)
Requires-Dist: jsonschema (>=4.23.0,<5.0.0)
Requires-Dist: openapi-core (>=0.19.0,<0.20.0)
Requires-Dist: pyyaml (>=6.0.1,<7.0.0)
Requires-Dist: requests (>=2.32.3,<3.0.0)
Requires-Dist: structlog (>=24.1.0,<25.0.0)
Project-URL: Documentation, https://github.com/fachrulch/berapi#readme
Project-URL: Homepage, https://github.com/fachrulch/berapi
Project-URL: Repository, https://github.com/fachrulch/berapi
